imageObjects/ContourObject.py
imageObjects/ImageObject.py
imageObjects/LineObject.py
imageObjects/PolySupport.py
imageObjects/__init__.py
imageObjects/Support/__init__.py
imageObjects/Support/_create_as_image.py
imageObjects/Support/_extract_from_image.py
imageObjects/Support/_misc.py
imageObjects-0.13.6.dist-info/LICENSE
imageObjects-0.13.6.dist-info/METADATA
imageObjects-0.13.6.dist-info/WHEEL
imageObjects-0.13.6.dist-info/top_level.txt
imageObjects-0.13.6.dist-info/RECORD
