Metadata-Version: 2.1
Name: imageObjects
Version: 0.13.6
Summary: Helper Objects for working with open computer vision and image projects
Home-page: UNKNOWN
Author: Samuel Baker
Author-email: samuelbaker.researcher@gmail.com
Maintainer: Samuel Baker
Maintainer-email: samuelbaker.researcher@gmail.com
License: MIT
Download-URL: https://github.com/sbaker-dev/contourObject
Platform: UNKNOWN
Classifier: Programming Language :: Python :: 3.7
Classifier: Programming Language :: Python :: 3.8
Classifier: License :: OSI Approved :: MIT License
Requires-Python: >=3.6
Requires-Dist: opencv-python
Requires-Dist: numpy
Requires-Dist: matplotlib
Requires-Dist: vectorObjects
Requires-Dist: shapely
Requires-Dist: miscSupports
